{
	"zh": [
        {
            "name": "癮雜誌 FLIPr",
            "description": "每日嗑雜誌，天天長知識。",
            "icon": "images/magazine/app_icon.png",
            "ios": "",
            "android": ""
        },
        {
            "name": "逢甲影音 FLIPr",
            "description": "逢甲大學新媒體，帶給全球創新價值，更是您無所不在的學習雲！",
            "icon": "images/fcu/app_icon.png",
            "ios": "https://itunes.apple.com/tw/app/feng-jia-ying-yin-flipr/id723980669?mt=8",
            "android": "https://play.google.com/store/apps/details?id=tw.edu.fcu.player9x9tv"
        },
        {
            "name": "喇新聞 FLIPr",
            "description": "茶餘飯後喇新聞，天下大事盡知曉。",
            "icon": "images/news/icon_200x200.png",
            "ios": "https://itunes.apple.com/tw/app/la-xin-wen-flipr/id865752513?l=zh&mt=8",
            "android": "https://play.google.com/store/apps/details?id=tv.flipr.news"
        },
        {
            "name": "MV不解釋 FLIPr",
            "description": "網羅YouTube超過萬首音樂MV，一指翻閱，簡單上手，輕鬆站在MV最前線！",
            "icon": "images/mv/icon_200x200.png",
            "ios": "https://itunes.apple.com/tw/app/mv-bu-jie-shi-flipr/id860501633?l=zh&mt=8",
            "android": "https://play.google.com/store/apps/details?id=tv.flipr.musicvideo"
        },
        {
            "name": "音樂圖書館 FLIPr",
            "description": "音樂就像一塊拼圖，總有屬於它的故事和適合的位置。証聲希望能幫每個音符都找到它的家！",
            "icon": "images/echomusic/app_icon.png",
            "ios": "",
            "android": ""
        },
        {
            "name": "網路大明星 FLIPr",
            "description": "千奇百怪的網路名人一籮筐。想走在潮流尖端，還沒下載「網路大明星 FLIPr」你就太弱了！",
            "icon": "images/superstar/icon_200x200.png",
            "ios": "https://itunes.apple.com/tw/app/wang-lu-da-ming-xing-flipr/id840776687?mt=8",
            "android": "https://play.google.com/store/apps/details?id=tv.flipr.superstar"
        },
        {
            "name": "關鍵評論網 FLIPr",
            "description": "News worth knowing, voices worth sharing 分享觀點從這開始",
            "icon": "images/thenewslens/icon_200x200.png",
            "ios": "https://itunes.apple.com/tw/app/guan-jian-ping-lun-wang-flipr/id842456259?l=en&mt=8",
            "android": "https://play.google.com/store/apps/details?id=tv.flipr.thenewslens"
        },
        {
            "name": "GOOD TV FLIPr",
            "description": "好消息電視台，是重視家庭價值、關懷社會與人心，帶給人們信心、希望、與真愛的電視台！",
            "icon": "images/goodtv/app_icon.png",
            "ios": "https://itunes.apple.com/tw/app/good-tv-flipr/id737001290?mt=8",
            "android": "https://play.google.com/store/apps/details?id=tv.goodtv.player9x9tv"
        },
        {
            "name": "華視 FLIPr",
            "description": "記憶中的老朋友，老三台「華視」創新APP。現在就來翻！給您驚奇無限。",
            "icon": "images/cts/app_icon.png",
            "ios": "https://itunes.apple.com/tw/app/hua-shi-flipr/id623085456?mt=8",
            "android": "https://play.google.com/store/apps/details?id=tw.com.cts.player"
        }
    ],
    "en" : [

         {

            "name": "Crash Course on FLIPr Unofficial",
            "icon": "images/crashcourse/icon_200x200.png",
            "description": "This app enables you to watch fun, educational videos from John & Hank Green's YouTube channel on-the-go, or on the big screen with Chromecast!",
            "ios": "https://itunes.apple.com/tw/app/crash-course-on-flipr-unoffical/id806472110?mt=8",
            "android": "https://play.google.com/store/apps/details?id=tv.flipr.crashcourse"
        },
        {

            "name": "Network A on FLIPr Unofficial",
            "icon": "images/networka/icon_200x200.png",
            "description": "Fill those 10-minute breaks with adrenaline-pumping stunts including skateboarding and much more on-the-go, or on the big screen with Chromecast! ",
            "ios": "",
            "android": "https://play.google.com/store/apps/details?id=tv.flipr.networka"
        },
        
        {

            "name": "CollegeHumor on FLIPr Unofficial",
            "icon": "images/collegehumor/icon_200x200.png",
            "description": "Fill those 10-minute breaks with fresh hilarious videos. Watch it continuously on-the-go, or on the big screen with Chromecast support!",
            "ios": "",
            "android": "https://play.google.com/store/apps/details?id=tv.flipr.collegehumor"
        },
        {

            "name": "Smosh on FLIPr Unofficial",
            "icon": "images/smosh/icon_200x200.png",
            "description": "Discover Anthony Padilla & Ian Hecox’s latest funnies on-the-go. This app can also help you watch it on the big screen with Chromecast support!",
            "ios": "",
            "android": "https://play.google.com/store/apps/details?id=tv.flipr.smosh"
        },
         {

            "name": "Shane on FLIPr Unofficial",
            "icon": "images/shane/icon_200x200.png",
            "description": "Discover the latest vlogs from actor, musician, comedian, and video maker - Shane Dawson! Watch it on the big screen with Chromecast support!",
            "ios": "",
            "android": "https://play.google.com/store/apps/details?id=tv.flipr.shane"
        },

         {

            "name": "TheFineBros on FLIPr Unofficial",
            "icon": "images/thefinebros/icon_200x200.png",
            "description": "Discover the latest videos of Kids/Teens/Elders/YouTubers React and many others on-the-go, or on the big screen with Chromecast support!",
            "ios": "https://itunes.apple.com/us/app/flipr-the-fine-bros-edition/id872233879?mt=8",
            "android": "https://play.google.com/store/apps/details?id=tv.flipr.thefinebros"
        },
        
        
        {

            "name": "NBA on FLIPr Unofficial",
            "icon": "images/nba/icon_200x200.png",
            "description": "Simply flip and discover the latest NBA moments all in an immersive experience. Watch it continuously on the big screen with Chromecast support! ",
            "ios": "",
            "android": "https://play.google.com/store/apps/details?id=tv.flipr.nba"
        },
        {

            "name": "History on FLIPr Unofficial",
            "icon": "images/history/icon_200x200.png",
            "description": "Discover the latest videos from the channel History. You can also watch it continuously on the big screen with our brand new Chromecast support!",
            "ios": "",
            "android": "https://play.google.com/store/apps/details?id=tv.flipr.history"
        },
        
       
        {

            "name": "SpinninRec on FLIPr Unofficial",
            "icon": "images/spinninrec/icon_200x200.png",
            "description": "Stay up to date with the latest electronic dance music from Spinnin’ Record! Take the music with you, or watch it on big screen with Chromecast!",
            "ios": "",
            "android": "https://play.google.com/store/apps/details?id=tv.flipr.spinninrec"
        },
       
        
        {

            "name": "JoeyGraceffa on FLIPr Unofficial",
            "icon": "images/joeygraceffa/icon_200x200.png",
            "description": "Discover the popular YouTuber Joey's new vlogs and old funnies on-the-go. You can also watch it continuously on the big screen with Chromecast!",
            "ios": "",
            "android": "https://play.google.com/store/apps/details?id=tv.flipr.joeygraceffa"
        },
        {

            "name": "丁丁電視, Ding Ding TV",
            "icon": "images/ddtv/icon_200x200.png",
            "description": "丁丁電視是美國首創華語網絡電視、矽谷創新頻道及視頻製作公司。Ding Ding TV is the first Chinese American Internet TV for Silicon Valley ",
            "ios": "https://itunes.apple.com/us/app/ding-ding-tv/id733144372?mt=8",
            "android": "https://play.google.com/store/apps/details?id=tv.ddtv.player9x9tv"
        }
    	
    ]
}